ewoksutils/__init__.py
ewoksutils/datetime_utils.py
ewoksutils/deprecation_utils.py
ewoksutils/event_utils.py
ewoksutils/import_utils.py
ewoksutils/path_utils.py
ewoksutils/sqlite3_utils.py
ewoksutils/task_utils.py
ewoksutils/uri_utils.py
ewoksutils/cli_utils/__init__.py
ewoksutils/cli_utils/cli_argparse.py
ewoksutils/cli_utils/cli_arguments.py
ewoksutils/cli_utils/cli_cancel_utils.py
ewoksutils/cli_utils/cli_click.py
ewoksutils/cli_utils/cli_execute_utils.py
ewoksutils/cli_utils/cli_log_utils.py
ewoksutils/cli_utils/cli_parse.py
ewoksutils/cli_utils/cli_spec.py
ewoksutils/cli_utils/cli_submit_utils.py
ewoksutils/logging_utils/__init__.py
ewoksutils/logging_utils/asyncwrapper.py
ewoksutils/logging_utils/cleanup.py
ewoksutils/logging_utils/connection.py
ewoksutils/logging_utils/sqlite3.py
ewoksutils/tests/__init__.py
ewoksutils/tests/conftest.py
ewoksutils/tests/test_cli.py
ewoksutils/tests/test_datetime.py
ewoksutils/tests/test_deprecated.py
ewoksutils/tests/test_import_utils.py
ewoksutils/tests/test_logging_utils.py
ewoksutils/tests/test_sqlite3_utils.py
ewoksutils/tests/test_task_utils.py
ewoksutils/tests/test_uri_utils.py
ewoksutils-1.9.1.dist-info/licenses/LICENSE.md
ewoksutils-1.9.1.dist-info/METADATA
ewoksutils-1.9.1.dist-info/WHEEL
ewoksutils-1.9.1.dist-info/top_level.txt
ewoksutils-1.9.1.dist-info/RECORD
