Metadata-Version: 2.4
Name: ewoksutils
Version: 1.9.1
Summary: Utilities for ewoks developers
Author-email: ESRF <dau-pydev@esrf.fr>
License: # MIT License
Project-URL: Homepage, https://gitlab.esrf.fr/workflow/ewoks/ewoksutils/
Project-URL: Documentation, https://ewoksutils.readthedocs.io/
Project-URL: Repository, https://gitlab.esrf.fr/workflow/ewoks/ewoksutils/
Project-URL: Issues, https://gitlab.esrf.fr/workflow/ewoks/ewoksutils/issues/
Project-URL: Changelog, https://gitlab.esrf.fr/workflow/ewoks/ewoksutils/-/blob/main/CHANGELOG.md
Classifier: Intended Audience :: Science/Research
Classifier: License :: OSI Approved :: MIT License
Classifier: Programming Language :: Python :: 3
Requires-Python: >=3.8
License-File: LICENSE.md
Provides-Extra: full
Requires-Dist: click; extra == "full"
Provides-Extra: test
Requires-Dist: ewoksutils[full]; extra == "test"
Requires-Dist: pytest>=7; extra == "test"
Provides-Extra: dev
Requires-Dist: ewoksutils[test]; extra == "dev"
Requires-Dist: black>=25; extra == "dev"
Requires-Dist: flake8>=4; extra == "dev"
Requires-Dist: isort; extra == "dev"
Provides-Extra: doc
Requires-Dist: sphinx>=4.5; extra == "doc"
Requires-Dist: sphinx-autodoc-typehints>=1.16; extra == "doc"
Requires-Dist: pydata-sphinx-theme; extra == "doc"
Requires-Dist: sphinx-copybutton; extra == "doc"
Dynamic: license-file
